gptindex/__init__.py
gptindex/__main__.py
ggptindex-0.1.dist-info/METADATA
ggptindex-0.1.dist-info/WHEEL
ggptindex-0.1.dist-info/entry_points.txt
ggptindex-0.1.dist-info/top_level.txt
ggptindex-0.1.dist-info/RECORD
