Metadata-Version: 2.1
Name: ggptindex
Version: 0.1
Requires-Dist: openai (==0.27.4)
Requires-Dist: langchain (==0.0.155)
Requires-Dist: prettytable (==3.7.0)
